{
  "users": [
    {
      "password": "1920343hjdwbhjk",
      "email": "hayk-ag942@mail.ru",
      "username": "Hayko",
      "token": "ju16xwvy",
      "id": 1
    },
    {
      "password": "poi876443etrg",
      "email": "abcde",
      "username": "vefsd",
      "token": "ju16ynef",
      "id": 2
    },
    {
      "password": "1023546eygdd",
      "email": "mnbgf",
      "username": "098754",
      "token": "ju1715bj",
      "id": 3
    },
    {
      "password": "s1213456789rdaszfxcvb",
      "email": "wedf",
      "username": "sanshhx",
      "token": "ju179klh",
      "id": 4
    },
    {
      "password": "",
      "email": "",
      "username": "",
      "token": "ju17b9ry",
      "id": 5
    },
    {
      "password": "6854711d288d9swkjsd",
      "email": "tkio98@mail.ru",
      "username": "Tigran",
      "token": "ju1k2fzp",
      "id": 6
    },
    {
      "password": "mhgtr5678998652",
      "email": "DSDSDS",
      "username": "hayko.js",
      "token": "ju1k5d3k",
      "id": 7
    },
    {
      "password": "",
      "email": "DSDSDSsss",
      "username": "hayko.js",
      "token": "ju1lcig6",
      "id": 8
    },
    {
      "password": "10241089hsyetgdwes",
      "email": "dinjan@bk,ru",
      "username": "Diana",
      "token": "ju1p3mpw",
      "id": 9
    },
    {
      "password": "324256",
      "email": "10241089hsyetgdwes",
      "username": "wertrew",
      "token": "ju1qd1b5",
      "id": 10
    },
    {
      "password": "q3ewrt",
      "email": "hayk-ag942@mail.u",
      "username": "hayko.js",
      "token": "ju1rabyv",
      "id": 11
    },
    {
      "password": "wqewrtyu",
      "email": "DSDSDdsfghjS",
      "username": "m_yan010",
      "token": "ju1rl9cx",
      "id": 12
    },
    [],
    {
      "password": "123456789",
      "email": "hayk-ag942@mail.umnhjgtfgh",
      "username": "m_yan0103215648532",
      "token": "ju2pwmpi",
      "id": 14
    },
    {
      "password": "",
      "email": "mozilllaaaaaaaaafbrgdhf",
      "username": "haykaret",
      "token": "ju319qsd",
      "id": 15
    },
    {
      "password": "",
      "email": "37494946828poiuhn",
      "username": "m_yan010",
      "token": "ju31don1",
      "id": 16
    },
    {
      "password": "",
      "email": "df",
      "username": "m_yan010",
      "token": "ju356hfx",
      "id": 17
    }
  ]
}